odoo/addons/mass_mailing_contact_active/README.rst
odoo/addons/mass_mailing_contact_active/__init__.py
odoo/addons/mass_mailing_contact_active/__manifest__.py
odoo/addons/mass_mailing_contact_active/i18n/es.po
odoo/addons/mass_mailing_contact_active/i18n/it.po
odoo/addons/mass_mailing_contact_active/i18n/mass_mailing_contact_active.pot
odoo/addons/mass_mailing_contact_active/models/__init__.py
odoo/addons/mass_mailing_contact_active/models/mailing_contact.py
odoo/addons/mass_mailing_contact_active/models/mailing_contact_subscription.py
odoo/addons/mass_mailing_contact_active/readme/CONTRIBUTORS.rst
odoo/addons/mass_mailing_contact_active/readme/CREDITS.rst
odoo/addons/mass_mailing_contact_active/readme/DESCRIPTION.rst
odoo/addons/mass_mailing_contact_active/static/description/icon.png
odoo/addons/mass_mailing_contact_active/static/description/index.html
odoo/addons/mass_mailing_contact_active/tests/__init__.py
odoo/addons/mass_mailing_contact_active/tests/test_mailing_contact_active.py
odoo_addon_mass_mailing_contact_active-16.0.1.0.0.9.dist-info/METADATA
odoo_addon_mass_mailing_contact_active-16.0.1.0.0.9.dist-info/WHEEL
odoo_addon_mass_mailing_contact_active-16.0.1.0.0.9.dist-info/top_level.txt
odoo_addon_mass_mailing_contact_active-16.0.1.0.0.9.dist-info/RECORD
